hpx/py.typed
hpx/_core.dll.a
hpx/_core.pyd
hpx/_core.pyi
hpx/__init__.py
hpx-0.1.0.dist-info/DELVEWHEEL
hpx-0.1.0.dist-info/METADATA
hpx-0.1.0.dist-info/RECORD
hpx-0.1.0.dist-info/WHEEL
hpx.libs/libgcc_s_seh-1-b338da2564bdf144bb8c9eddfbcd1b65.dll
hpx.libs/libgmp-10-c272a495a0a94982ebfbecbe66b684d0.dll
hpx.libs/libstdc++-6-87cff402cb4dbb36c1f110db99a645a9.dll
hpx.libs/libwinpthread-1-0caa31423d3b918071b0d9ad81fe2ef3.dll
