Metadata-Version: 2.4
Name: hpx
Version: 0.1.0
Summary: Multiresolution HEALPix sampling and adaptive grids
Author-Email: Leo Singer <leo.p.singer@nasa.gov>
License-Expression: Apache-2.0
Classifier: Development Status :: 1 - Planning
Classifier: Operating System :: MacOS
Classifier: Operating System :: Microsoft :: Windows
Classifier: Operating System :: POSIX
Classifier: Operating System :: POSIX :: Linux
Classifier: Operating System :: Unix
Classifier: Programming Language :: Python :: 3 :: Only
Classifier: Topic :: Scientific/Engineering :: Astronomy
Classifier: Typing :: Typed
Project-URL: GitHub, https://github.com/nasa-gcn/hpx
Requires-Python: >=3.11
Requires-Dist: numpy>=1.23
Provides-Extra: doc
Requires-Dist: sphinx-astropy[confv2]; extra == "doc"
Provides-Extra: test
Requires-Dist: astropy; extra == "test"
Requires-Dist: pytest; extra == "test"
Requires-Dist: pytest-benchmark; extra == "test"
Requires-Dist: scipy; extra == "test"
